{
    "batteryOptimizationSettingsUnavailable": "电池优化设置不可用",
    "appVersion": "版本",
    "okBtn": "好",
    "gotItBtn": "好的，明白了",
    "backBtn": "返回",
    "addBtn": "添加",
    "saveBtn": "保存",
    "selectBtn": "选择",
    "cancelBtn": "取消",
    "resetBtn": "重置",
    "deleteBtn": "删除",
    "removeBtn": "移除",
    "browseBtn": "浏览",
    "discardBtn": "丢弃",
    "updateBtn": "更新",
    "createBtn": "创建",
    "continueBtn": "继续",
    "abortBtn": "中止",
    "yesBtn": "是",
    "noBtn": "否",
    "none": "无",
    "notReallyBtn": "不完全是",
    "askMeLaterBtn": "稍后再问我",
    "mayBeLaterBtn": "可能稍后",
    "noThanksBtn": "不，谢谢",
    "okSureBtn": "好的，当然",
    "doneBtn": "完成",
    "infoTxt": "信息",
    "exceptionTxt": "异常",
    "alert": "警报！",
    "oops": "哎呀！",
    "attention": "注意！",
    "pleaseWait": "请等待",
    "exit": "退出",
    "left": "左",
    "right": "右",
    "center": "中间",
    "small": "小",
    "medium": "中",
    "large": "大",
    "second": "秒",
    "minute": "分",
    "hour": "时",
    "day": "天",
    "signIn": "登录",
    "signUp": "注册",
    "signOut": "退出登录",
    "forgotPassword": "忘记密码",
    "resetPassword": "重置密码",
    "refreshBtn": "刷新",
    "resendEmail": "重新发送电子邮件",
    "createNewAccount": "创建新的",
    "privacyStatement": "注册即表示您接受",
    "doNotHaveAccount": "没有账户？",
    "alreadyHaveAccount": "已有账户？",
    "resetPasswordInstruction": "重置密码链接已发送至您的电子邮件。点击该链接可设置新密码。",
    "regexErrorHost": "无效的主机地址",
    "regexErrorHostExtended": "无效的主机地址",
    "rangeErrorPort": "无效的端口",
    "rangeErrorKeepAlive": "允许0或60-86400",
    "regexErrorTopic": "不允许使用通配符",
    "regexErrorTopicWildCard": "无效的主题",
    "regexErrorInteger": "只允许使用整数",
    "regexErrorFloat": "只允许使用数字",
    "rangeErrorLogLength": "允许1-100",
    "rangeErrorMaxPersistence": "允许0-1000",
    "rangeErrorMessageNonZero": "不允许0",
    "rangeErrorRefreshInterval": "允许5-3600",
    "whatsNewTitle": "有什么新内容？",
    "newFeaturesTitle": "新功能",
    "legacyMigrateTitle": "无法自动迁移配置",
    "legacyMigrateDescription": "您正在尝试从一个太旧的版本升级，该版本无法自动迁移。您需要执行以下步骤进行手动迁移。",
    "legacyImportWarning": "这将替换您现有的配置。确保您已备份配置。要继续吗？",
    "legacyMigrateStep1": "步骤 1：备份当前配置",
    "legacyMigrateStep2": "步骤 2：恢复相同配置",
    "legacyMigrateStep3": "步骤 3：退出并重新启动应用程序",
    "infoTitle": "应用程序信息",
    "infoSection": "信息部分",
    "aboutTitle": "关于",
    "freeVersionTitle": "免费版",
    "buyProBtn": "购买专业版",
    "freeVersionDesc": "您可以购买专业版以移除广告并鼓励开发。",
    "proVersionTitle": "专业版",
    "proVersionDesc": "非常感谢您购买本应用程序。这将鼓励我们的开发工作",
    "rateAppTitle": "为应用程序评分",
    "rateAppBtnTxt": "评分",
    "rateAppDesc": "如果您喜欢这款应用程序，请给予好评。这将激励我们继续开展该项目。",
    "privacyPolicy": "隐私政策",
    "followUs": "关注我们",
    "welcomeTitle": "欢迎",
    "appSettingsTitle": "应用设置",
    "darkTheme": "黑暗主题",
    "wakeLock": "保持屏幕常亮",
    "runInBackground": "后台运行",
    "disableBatteryOptimization": "禁用电池优化",
    "selectLanguage": "选择语言",
    "orientation": "方向",
    "landscape": "横向",
    "defaultConnection": "默认连接",
    "portrait": "纵向",
    "dashboardListPlacement": "仪表盘列表放置",
    "titleBar": "标题栏",
    "bottomBar": "底栏",
    "disableBackgroundRunAlert": "使用返回按钮退出应用时，后台服务将终止。按下主屏或最近应用按钮将保持应用在后台运行。这也适用于手势导航。",
    "backgroundRunForPermission": "后台服务仅在启用通知时有效。请从设置中启用通知，然后重新启动应用。",
    "errorTitle": "错误",
    "cleanAppData": "清理应用程序数据",
    "somethingWentWrong": "出了问题",
    "errorPageMessage1": "抱歉，发生了意外错误。",
    "errorPageMessage2": "如果您使用快捷方式启动应用程序，该快捷方式可能不再有效。请重新创建仪表板快捷方式。",
    "errorPageMessage3": "此错误也可能是由于数据或配置损坏引起的。如果它发生在特定的连接、仪表板或面板，请删除并重新配置后再试。",
    "errorPageMessage4": "果问题仍然存在，您可以清除该应用的所有数据并重新配置。",
    "connectionTitle": "连接",
    "connectionsListEmpty": "您没有任何与MQTT代理通讯的连接。如果您是第一次使用此应用程序，我们强烈建议您阅读主菜单中的常见问题和用户指南。",
    "addConnections": "设置连接",
    "connectionDeleteMessage": "您确定要删除连接设置吗？所有相关的仪表盘和面板都将丢失。",
    "feedbackDialogTitle": "喜欢物联网MQTT面板吗？",
    "rateAppDialogTitle": "那么在应用商店给个评价怎么样？",
    "leaveCommentDialogTitle": "您能给我们一些反馈意见吗？",
    "cloneConnection": "克隆连接",
    "cloneConnectionContent": "重复的客户 ID 可能会导致连接终止。留空可随机生成。",
    "shareConnectionTitle": "通过MQTT共享",
    "publishConnection": "发布此连接",
    "receiveConnection": "订阅并等待",
    "connectingToBroker": "连接到代理",
    "waitingForConfiguration": "等待配置",
    "failedToImport": "导入数据失败",
    "failedToExport": "导出数据失败",
    "failedToShage": "共享数据失败",
    "shareDisclaimer": "注意：您可以通过MQTT发送或接收此连接下的仪表板。请记住，在接收时所有现有的仪表板将被替换。",
    "shareVersionMismatch": "配置不能在两个不同版本的应用程序之间共享。请更新两个应用程序并重试。",
    "configurationSent": "配置已发布",
    "configurationReceived": "配置已接收",
    "addDashboardTitle": "添加仪表板",
    "editDashboardTitle": "编辑仪表板",
    "cloneDashboard": "克隆仪表板",
    "dashboardName": "仪表板名称",
    "dashboardNameRequired": "仪表板名称是必填项",
    "dashboardPrefixTopic": "仪表板前缀主题",
    "dashboardPrefix": "仪表板前缀",
    "dashboardPrefixHelp": "此仪表板的可选前缀。对于公共代理很有用",
    "setConnectionHomeHelp": "选择此选项将允许仪表板在选择连接时默认打开",
    "setConnectionHome": "设置为连接主页",
    "dashboardColor": "仪表板主题颜色",
    "dashboardIcon": "选择仪表板图标",
    "lockPanels": "锁定面板",
    "addConnectionTitle": "添加连接",
    "editConnectionTitle": "编辑连接",
    "connectionName": "连接名称",
    "connectionNameRequired": "连接名称是必填项",
    "connectionNameHelp": "友好连接名称",
    "clientId": "客户端ID",
    "clientIdHelp": "输入客户端ID或留空以随机生成",
    "hostAddress": "代理Web/IP地址",
    "hostAddressRequired": "代理主机地址是必填项",
    "hostAddressHelp": "MQTT代理的DNS/IP地址，例如test.mosquitto.org或192.168.1.5",
    "portNumber": "端口",
    "portNumberRequired": "端口号是必填项",
    "networkProtocol": "网络协议",
    "networkTCP": "TCP",
    "networkSSL": "TCP-SSL",
    "networkWebsocket": "Websocket",
    "networkSecureWebsocket": "Websocket-SSL",
    "networkHelp": "您可以选择TCP（默认）或Websocket连接。对于带证书的加密安全连接，选择SSL。通常TCP、TCP（SSL）、Websocket和Websocket（SSL）的端口分别为1883、8883、8080和8081。",
    "certHelp": "为SSL添加crt/pem证书路径。您可以提供CA或自签名证书。由于Android范围存储限制，此文件将被复制到应用的内部存储中。有关更多信息，请参阅用户指南。",
    "sslConfiguration": "管理SSL配置",
    "disableHostnameCheck": "禁用主机名(SAN)检查",
    "disableHostnameCheckWarning": "警告：证书主题备用名称将不被验证。",
    "allowUntrustCACertificate": "允许使用不受信任的证书",
    "allowUntrustCACertificateWarning": "警告：代理身份将不被验证。",
    "tlsVersion": "TLS版本",
    "caCertificate": "CA证书",
    "caCettificateHelp": "您可以在此使用自己签署的CA 证书。请参阅 \"帮助和常见问题 \"部分，了解如何生成证书。",
    "clientCertificate": "客户端证书（PKCS12）",
    "clientCertificateHelp": "您可以使用PKCS12证书进行客户端身份验证。如果您有单独的客户端证书和私钥，请使用OpenSSL生成此证书。导出密码不能为空，并使用OpenSSL版本1.1或-legacy标志正确生成它。有关更多信息，请参阅帮助和常见问题部分。",
    "clientKey": "客户端密钥",
    "exportPassword": "导出密码",
    "exportPasswordRequired": "导出密码是必填项",
    "dashboardList": "仪表板列表",
    "dashboardRequired": "至少需要一个仪表板",
    "aditionalOptions": "附加选项",
    "keepAlive": "保持存活",
    "keepAliveRequired": "保持存活是必填项",
    "keepAliveHelp": "保持存活时间（默认60）",
    "cleanSession": "清除会话",
    "name": "名称",
    "nameRequired": "名称是必填项",
    "email": "邮箱",
    "emailRequired": "邮箱是必填项",
    "invalidEmail": "邮箱无效",
    "username": "用户名",
    "password": "密码",
    "passwordRequired": "密码是必填项",
    "usernamePasswordHelp": "可选的用户名和密码用于身份验证",
    "autoConnect": "自动连接",
    "notifyOnDisconnect": "断开连接时通知",
    "dashboardDeleteFailMessage": "您无法删除连接的主页仪表板。将另一个仪表板设为连接主页，然后删除此仪表板。",
    "enableWillMessage": "启用遗嘱消息",
    "scanFailed": "扫描失败",
    "scanNotSupported": "不支持扫描",
    "cameraPermissionDenied": "需要相机权限",
    "scanModuleInstalling": "正在安装Google条码扫描器",
    "scanModuleInstalled": "Google条码扫描器已安装。您现在可以扫描了。",
    "scanModuleInstallFailed": "安装Google条码扫描器失败。更新Google Play服务后重试。",
    "scan canceled.": "扫描已取消",
    "The Google Barcode Scanner Module is not available. You must install it first.": "扫描模块尚未准备好。稍后再试。",
    "addNewDashboard": "添加新仪表板",
    "addPanel": "添加面板",
    "editPanel": "编辑面板",
    "editThisPanel": "编辑此面板",
    "clonePanel": "克隆面板",
    "deletePanel": "删除此面板",
    "movePanelUp": "向前移动",
    "movePanelDown": "向后移动",
    "mergeLeft": "向左合并",
    "mergeRight": "向右合并",
    "mergeTop": "向上合并",
    "mergeBottom": "向下合并",
    "deletePanelData": "删除数据",
    "exportPanelData": "导出数据",
    "exportPanelDataTitle": "导出面板数据",
    "exportDataNotAllowed": "仅专业版允许导出数据",
    "shareConfigNotAllowed": "仅专业版允许共享配置",
    "panelDeleteConfirmation": "您确定要删除此面板吗？",
    "panelDataDeleteConfirmation": "您确定要删除此面板的持久数据吗？",
    "selectPanelType": "选择要添加的面板类型",
    "panelListEmpty": "当前仪表板没有任何面板",
    "toastSyncReqPublished": "已发布同步请求",
    "dashboardCloneSuccess": "仪表板已成功克隆",
    "clonablePanelEmpty": "未找到要克隆的面板",
    "shortcutCreateError": "无法创建快捷方式",
    "shortcutDoesNotSupported": "不支持快捷方式",
    "createShortcut": "创建快捷方式",
    "invalidShortcut": "已废弃的快捷方式，请重新生成一个新的",
    "deleteDashboard": "删除此仪表板",
    "dashboardDeleteConfirmMessage": "您确定要删除此仪表板吗？所有相关面板都将丢失。",
    "panelLabelButton": "按钮",
    "panelLabelSwitch": "开关",
    "panelLabelSlider": "滑块",
    "panelLabelComboBox": "组合框",
    "panelLabelRadioButtons": "单选按钮",
    "panelLabelLEDIndicator": "LED指示灯",
    "panelLabelMultistateIndicator": "多态指示器",
    "panelLabelProgress": "进度",
    "panelLabelGauge": "量表",
    "panelLabelTextInput": "文本输入",
    "panelLabelTextLog": "文本日志",
    "panelLabelColorPicker": "颜色选择器",
    "panelLabelDateTimePicker": "日期和时间选择器",
    "panelLabelLineGraph": "折线图",
    "panelLabelBarGraph": "条形图",
    "panelLabelChart": "图表",
    "panelImageViewer": "图片",
    "panelLabelBarcodeScanner": "条码扫描器",
    "panelLabelURILauncher": "URI启动器",
    "panelLabelNodeStatus": "节点状态",
    "panelLabelLayoutDecorator": "布局装饰器",
    "panelInfoButton": "按下按钮发布预配置的负载。",
    "panelInfoSwitch": "发布负载以打开或关闭设备。它还订阅主题以监控其状态。",
    "panelInfoSlider": "从配置的范围发布一个数字并订阅主题以显示状态。",
    "panelInfoComboBox": "从预配置列表发布和订阅负载。列表较大时，请使用此面板而不是单选按钮面板。",
    "panelInfoRadioButtons": "从预配置列表发布和订阅负载。列表较小时，请使用此面板而不是组合框面板。",
    "panelInfoLEDIndicator": "订阅主题并显示开或关状态。这是一个只读面板。要发布负载，请使用开关面板。",
    "panelInfoMultistateIndicator": "订阅主题并显示状态如果与预配置的负载列表匹配。这是一个只读面板。要发布负载，请使用组合框或单选按钮面板。",
    "panelInfoProgress": "订阅主题并在水平、垂直或圆形条上显示进度。这是一个只读面板。要发布负载，请使用滑块面板。",
    "panelInfoGauge": "订阅主题并在量表上显示进度。它可以配置三种不同的颜色，这些颜色将根据负载变化。",
    "panelInfoTextInput": "从文本框发布任何消息到预配置主题。",
    "panelInfoTextLog": "此面板订阅一个主题并显示其负载。此面板允许使用通配符订阅。可以配置为显示所有接收到的负载或最新消息。",
    "panelInfoColorPicker": "显示色板，以 HEX 或 RGB 格式选择和发布颜色。",
    "panelInfoDateTimePicker": "显示一个日期和时间选择器以选择并发布。还允许单击发布当前日期和时间。",
    "panelInfoLineGraph": "实时绘制负载值。多个主题可以绘制在一个图中。",
    "panelInfoBarGraph": "在单个条形图中绘制一个或多个主题的最新有效载荷。",
    "panelInfoChart": "绘制多个主题的最新负载在饼图或甜甜圈图中。",
    "panelInfoImageViewer": "显示来自静态 URL 或通过 MQTT 接收到的图像",
    "panelInfoBarcodeScanner": "扫描条形码或二维码码并发布解码值",
    "panelInfoURILauncher": "订阅主题并按下启动按钮后在适当的应用程序中打开最新的URL，例如浏览器、地图等。",
    "panelInfoNodeStatus": "它有助于显示是否有远程设备（例如ESP32或树莓派）连接到代理。请记住，此面板无法开箱即用。远程设备在连接后必须发布在线负载，并应将离线负载配置为带有保留标志的遗嘱消息。点击状态图标也可以发布手动同步请求。\n",
    "panelInfoLayoutDecorator": "此面板仅用于视觉装饰。它有助于为多个面板组合创建标题。",
    "addButtonPanelTitle": "添加一个按钮面板",
    "addSwitchPanelTitle": "添加一个开关面板",
    "addSliderPanelTitle": "添加一个滑块面板",
    "addComboBoxPanelTitle": "添加一个组合框面板",
    "addRadioButtonsPanelTitle": "添加一个单选按钮面板",
    "addLEDIndicatorPanelTitle": "添加一个LED指示灯面板",
    "addMultistateIndicatorPanelTitle": "添加一个多状态指示器",
    "addProgressPanelTitle": "添加一个进度面板",
    "addGaugePanelTitle": "添加一个量表面板",
    "addTextInputPanelTitle": "添加一个文本输入面板",
    "addTextLogPanelTitle": "添加一个文本日志面板",
    "addColorPickerPanelTitle": "添加一个颜色选择器面板",
    "addTimePickerPanelTitle": "添加一个日期时间选择器面板",
    "addLineGraphPanelTitle": "添加一个折线图面板",
    "addBarGraphPanelTitle": "添加一个条形图面板",
    "addChartPanelTitle": "添加一个图表面板",
    "addImageViewerPanelTitle": "添加一个图像面板",
    "addBarcodePanelTitle": "添加一个条码扫描仪面板",
    "addURILauncherPanelTitle": "添加一个URI启动器面板",
    "addNodeStatusTitle": "添加一个节点状态面板",
    "addLayoutDecoratorTitle": "添加一个布局装饰面板",
    "allConnections": "所有连接",
    "dashboardConfigurations": "仪表板配置",
    "dashboardQuickAccess": "仪表板快速访问",
    "discardMessage": "您确定要放弃更改吗？",
    "formValidationFailed": "先修复上述错误",
    "unit": "单位",
    "color": "颜色",
    "dynamicColor": "动态颜色",
    "factor": "系数",
    "url": "URL",
    "disableDashboardPrefix": "禁用仪表板前缀主题",
    "disableDashboardPrefixHelp": "面板前缀会自动预置到面板主题中。禁用它可排除此面板。",
    "iconSize": "图标大小",
    "buttonSize": "按钮大小",
    "buttonColor": "按钮颜色",
    "switchColor": "开关颜色",
    "sliderColor": "滑块颜色",
    "sliderOrientation": "滑块方向",
    "progressOrientation": "进度类型",
    "sliderStep": "滑块步长",
    "sliderStepRequired": "滑块步长是必填项",
    "fitToPanelWidth": "适合面板宽度",
    "hideLabel": "隐藏标签",
    "labelForItem": "项目标签",
    "topicForItem": "项目主题",
    "itemLabelRequired": "项目标签是必填项",
    "addRadioOption": "添加单选项目",
    "deleteThisRadioOption": "删除此单选项目",
    "useIconOption": "为选项使用图标",
    "addComboOption": "添加项目",
    "deleteThisComboOption": "删除此项目",
    "noOfLastMessage": "最大可见行数",
    "maxPersistenceMessage": "最大持续性",
    "maxPersistenceHelp": "应用在后台运行时的最大持续信息数",
    "maxDuraion": "最长持续时间",
    "maxDuraionHelp": "数据点在此持续时间之后将不可见",
    "smoothCurve": "平滑曲线",
    "smoothCurveHelp": "图形线将被平滑处理，而不是直线。启用该功能将导致数据点数量增加时性能下降。\n",
    "required": "必要",
    "payloadMin": "最小有效载荷",
    "payloadMinRequired": "最小负载是必填项\n",
    "payloadMax": "最大有效载荷",
    "payloadMaxRequired": "最大负载是必填项\n",
    "payloadMaxGtMin": "最大值必须大于最小值\n",
    "payloadMaxNotEqMin": "最大值和最小值不得相等",
    "payloadOn": "负载开",
    "payloadOnRequired": "负载开是必填项",
    "payloadOff": "负载关",
    "payloadOffRequired": "负载关是必填项",
    "payloadOnline": "在线有效载荷",
    "payloadOnlineRequired": "在线负载是必填项",
    "payloadOffline": "离线负载",
    "payloadOfflineRequired": "离线负载是必填项",
    "payloadSyncRequest": "同步请求负载",
    "payloadSyncRequestRequired": "同步请求负载是必填项",
    "payloadForItem": "项目有效载荷",
    "duplicatePayloadsNotAllowed": "不允许重复有效载荷",
    "enableNotification": "启用通知",
    "valueMin": "最小值",
    "valueMinRequired": "最小值是必填项",
    "valueMax": "最大值",
    "valueMaxRequired": "最大值是必填项",
    "matchingValue": "匹配值",
    "matchingVaueRequired": "匹配值是必填项",
    "addMatchingValue": "添加更多匹配值",
    "regEx": "（RegEx）正则表达式",
    "regExRequired": "（RegEx）正则表达式是必填项",
    "notificationMessage": "通知信息",
    "notificationMessageHelp": "定义您要在通知中显示的消息。负载值可以用<payload>占位符替换。",
    "notificationFilter": "何时触发通知？",
    "notifyAll": "始终通知",
    "valueChanged": "值更改",
    "notifyEqualsTo": "等于",
    "notifyEqualsToNumber": "等于数字",
    "notifyBellowMin": "低于阈值",
    "notifyAboveMax": "高于阈值",
    "notifyWithinRange": "在范围内",
    "notifyExcludeRange": "排除范围",
    "notifyMatchingValue": "值匹配",
    "notifyMatchingString": "匹配字符串",
    "notifyMatchingRegex": "匹配正则（RegEx）",
    "notificationHelp": "此功能仅在专业版中提供",
    "noWildcardNotification": "通知不适用于通配符",
    "showLatestMsgOnly": "仅显示最后一条信息",
    "showReceivedTimeStamp": "显示接收时间戳",
    "showSentTimeStamp": "显示发送时间戳",
    "hideTopic": "隐藏主题",
    "textSize": "文字大小",
    "digitalDisplay": "数字字体",
    "isJSONPayload": "负载是JSON数据",
    "jsonPath": "订阅的JsonPath",
    "jsonEnvelope": "发布的JSON模式",
    "addAlpha": "添加alpha",
    "hideColorValue": "隐藏颜色值",
    "ledColor": "LED颜色",
    "ledOnIcon": "LED开图标",
    "ledOffIcon": "LED关图标",
    "colorRequired": "颜色是必填项",
    "iconColor": "图标颜色",
    "chooseIcon": "选择图标",
    "chooseOnIcon": "开图标",
    "chooseOffIcon": "关图标",
    "useIconSwitch": " 使用图标开关",
    "colorRange": "颜色范围",
    "arcColor": "弧线颜色",
    "chartColor": "图表颜色",
    "barColor": "条形颜色",
    "graphColor": "图表颜色",
    "pieChartType": "图表类型",
    "pieChart": "饼图",
    "donutChart": "甜甜圈图",
    "topicForBar": "条形主题",
    "labelForBar": "条形标签",
    "addMoreBar": "添加更多条形",
    "deleteThisBar": "删除此条形",
    "vertical": "垂直",
    "horizontal": "水平",
    "circular": "圆形",
    "topicForGraph": "图形主题",
    "labelForGraph": "图形标签",
    "addMoreGraph": "添加更多图形",
    "deleteThisGraph": "删除此图形",
    "noOfAxisDivisor": "X轴除数",
    "showArea": "显示绘图区域",
    "showPoints": "显示点和工具提示",
    "auto": "自动",
    "defineRange": "定义范围",
    "hideTimestamp": "隐藏时间戳",
    "launchUri": "启动URI",
    "restrictHeight": "限制高度",
    "titleAlignment": "标题对齐",
    "imageSource": "图片来源",
    "urlPayload": "URL有效载荷",
    "base64Payload": "Base64有效载荷",
    "staticUrl": "静态URL",
    "urlRequired": "URL是必填项",
    "clearTextOnPublish": "发布时清除文本",
    "pickerType": "选择器类型",
    "time": "时间",
    "date": "日期",
    "dateTime": "日期时间",
    "currentDate": "当前日期",
    "currentTime": "当前时间",
    "currentDateTime": "当前日期时间",
    "nodeStatusColor": "状态颜色",
    "nodeStatusOnlineIcon": "在线图标",
    "nodeStatusOfflineIcon": "离线图标",
    "autoSync": "加载时自动同步",
    "autoRefresh": "自动刷新",
    "refreshInterval": "自动刷新时间间隔",
    "layoutDecoratorFormDesc": "此面板既不订阅也不发布任何数据。此面板仅用于装饰目的。它有助于为组合面板创建标题标签。",
    "panelName": "面板名称",
    "hidePanelNameWarning": "面板名称对该面板不可见",
    "panelNameRequired": "面板名称是必填项",
    "topic": "主题",
    "seperateSubscribeTopic": "订阅主题",
    "topicRequired": "主题是必填项",
    "payload": "有效载荷",
    "payloadRequired": "负载是必填项",
    "addAditionalItem": "添加更多项目",
    "deleteThisItem": "删除此项目",
    "jsonPathRequired": "JsonPath是必填项",
    "jsonEnvelopeRequired": "JSON模式是必填项",
    "oneJsonRequired": "JsonPath或JSON模式是必填项",
    "qos": "QoS",
    "retain": "保留",
    "panelWidth": "面板宽度",
    "panelWidth100": "全屏",
    "panelWidth66": "2/3屏宽",
    "panelWidth50": "1/2屏宽",
    "panelWidth33": "1/3屏宽",
    "panelWidth25": "1/4屏宽",
    "jsonPathHelp": "提供JsonPath以解析接收到的消息中的JSON数据。请参阅用户指南以获取使用详情。",
    "jsonEnvelopeHelp": "您可以将发布消息包装为JSON格式。请参阅用户指南以获取使用详情。有效的可替换变量有 {{options}}",
    "seperateSubscribeTopicHelp": "如果希望使用与发布主题不同的订阅主题，请提供订阅主题。如果与发布主题相同，则留空。",
    "noPayload": "无有效载荷",
    "noPayloadHelp": "发布的报文没有有效载荷。这有时有助于清除代理中保留的消息。",
    "confirmBeforePublish": "发布前确认",
    "confirmationMessage": "确认消息",
    "confirmationMessageRequired": "确认消息是必填项",
    "confirmationMessageHelp": "定义您要在确认框中显示的消息。负载值可以用<payload>占位符替换。",
    "notAvailableOnThisPlatform": " 此平台不可用",
    "connectionInProgress": "尝试连接代理",
    "alreadyConnected": "已连接",
    "clientNotConnected": "应用未连接",
    "failedToConnect": "连接失败",
    "connectionLost": "连接丢失",
    "Not authorized to connect": "无权连接",
    "Client disconnected": "连接终止",
    "Client not connected": "客户端未连接",
    "Shortcut is not supported": "此设备不支持快捷方式",
    "Failed to export": "导出失败",
    "Export cancelled": "取消导出",
    "Failed to import": "导入失败",
    "Import cancelled": "取消导入",
    "Failed to parse number": "解析数字失败",
    "Failed to publish": "发布失败",
    "Configuration updated": "配置已更新",
    "Permission denied": "权限被拒绝",
    "backupTitle": "备份和恢复",
    "backupLabel": "备份",
    "restoreLabel": "恢复",
    "shareConfig": "共享配置",
    "excludeBrokerInfo": "排除代理信息？",
    "excludeBrokerInfoDetails": "这将在导出配置时排除每个连接中的代理地址、客户端 ID、用户名和密码。",
    "backupDisclaimer": "备份将导出配置，可以快速共享以设置新设备。导出的配置是包含敏感信息的未加密纯文本文件，例如代理用户名和密码。不要将此文件共享给未授权的人。此外，证书文件不会导出。您必须手动备份这些文件。",
    "randomizeClientId": "不同的MQTT客户端使用相同的客户端ID可能会自动终止连接。您是否希望为每个连接随机生成客户端ID？",
    "invalidSchemaWarning": "JSON模式验证失败。这可能是由于数据无效或版本不匹配。如果继续，您可能会遇到配置问题。我们强烈建议在导入前导出当前设置作为备份。您仍然要继续导入吗？",
    "configImportSuccess": "配置已导入",
    "configImportFailure": "无法导入配置",
    "configExportSuccess": "配置已导出",
    "configExportFailure": "无法导出配置",
    "exportDataSuccess": "数据已导出",
    "exportDataFailure": "无法导出数据",
    "configShareSuccess": "配置已共享",
    "configShareFaiure": "共享配置失败",
    "myProfileTitle": "我的资料",
    "deleteProfile": "删除资料",
    "impersonateUser": "模拟用户",
    "impersonateBtn": "模拟",
    "impersonating": "正在模拟",
    "endImpersonation": "结束模拟",
    "selectUser": "选择用户",
    "impersonateSettingsTitle": "模拟设置",
    "adminPrivilege": "管理员权限",
    "generateRandomClientId": "生成随机客户端ID",
    "clientIdConflictDisclaimer": "在多个应用程序中使用相同的客户端ID会导致循环重新连接。重新生成随机客户端 ID 可避免这种情况。",
    "profileDeleteMessage": "您确定要删除您的帐户吗？一旦删除，管理员重新配置应用之前您将无法使用该应用。",
    "emailVerificationTitle": "您的邮箱正在验证中",
    "emailVerificationDesc": "您将收到一封验证电子邮件。请检查您的邮箱并按照说明操作。",
    "verificationEmailSent": "验证邮件已发送",
    "adminApprovalTitle": "等待管理员批准",
    "adminApprovalDesc1": "您的电子邮件已通过验证，请联系您的管理员将您添加为团队成员。",
    "adminApprovalDesc2": "如果您是管理员并希望创建自己的团队，请通过电子邮件联系我们。",
    "noAdminProfileTitle": "您没有资料",
    "noAdminProfileDesc1": "您没有配置文件。请将您的配置文件添加到您的团队。",
    "noAdminProfileDesc2": "由于您是管理员，您也可以在不创建资料的情况下模拟您的团队成员。",
    "profileDisableTitle": "您的帐户已禁用",
    "profileDisableDesc1": "您的帐户已被管理员禁用。请联系管理员重新启用。",
    "profileDisableDesc2": "如果您想更换管理员，可以删除您的个人资料，然后使用新管理员重新创建账户。",
    "helpTitle": "帮助",
    "userGuide": "用户指南",
    "userGuideDesc": "有关详细信息和帮助，请参阅《用户指南》。如果您有任何问题、发现任何错误或需要新功能，请在我们的博客上留言。",
    "visitToBlog": "访问博客",
    "helpFaqTitle": "帮助和常见问题",
    "faqTitle": "常见问题",
    "faqPlafromQ": "该应用在哪些平台上可用？",
    "faqPlafromA": "该应用程序可在 Android 和 iOS 上使用。",
    "faqPrivacyQ": "数据隐私如何？",
    "faqPrivacyA": "本应用既不收集任何数据也不与任何第三方共享。所有数据和用户偏好都保存在本地内存中。然而，用户可以随时导出他的偏好，可能包含敏感信息，用户有责任确保导出数据的安全。此外，该应用显示来自Google AdSense的广告。请参阅Google AdSense隐私政策以了解有关广告的更多信息。",
    "faqProtocolsQ": "支持哪些协议？",
    "faqProtocolsA": "此应用程序支持MQTT（TCP）和Websocket协议。",
    "faqSecurityQ": "是否支持TLS/SSL？",
    "faqSecurityA": "是的，它支持TLS。在iOS中，您只能使用受信任的CA提供的证书。而在Android中，您可以使用受信任的CA证书或自签名x509证书进行加密。使用Linux OpenSSL可以使用以下命令生成证书。",
    "faqClientCertificateQ": "是否支持客户端证书验证？",
    "faqSecurityAopenssl": "openssl req -x509 -newkey rsa:4096 -sha256 -days 3650 -nodes -keyout snr-key.key -out snr-crt.crt -subj \"/CN=example.com\" -addext \"subjectAltName=DNS:example.com,IP:10.0.2.2,IP:192.168.0.150\"",
    "faqClientCertificateA": "是的，它支持使用 PKCS12 证书进行客户端验证。如果单独拥有客户端证书和私钥，请使用 OpenSSL 生成该证书。导出密码不能为空，并使用 OpenSSL 1.1 版本或-legacy 标志。否则，证书可能无法正常导入。在终端中使用以下命令生成证书。",
    "faqQosQ": "支持哪些QoS？",
    "faqQosA": "支持QoS 0、1 和 2。",
    "faqWildCardQ": "它支持通配符订阅吗？",
    "faqWildCardA": "是的，它支持在适用的地方使用通配符订阅（例如，日志面板）。",
    "faqDataTypeQ": "有效载荷的数据类型是什么？",
    "faqDataTypeA": "为使应用程序保持简洁，所有有效载荷均以字符串类型实现。",
    "faqJsonQ": "它支持JSON数据吗？",
    "faqJsonA": "是的，它支持JSON数据。",
    "faqJsonASubscribeTitle": "订阅 JSON 数据：",
    "faqJsonASubscribe": "您可以使用简单的JsonPath解析接收到的消息。支持的JsonPath如下所示。",
    "faqJsonAPathRoot": "根对象/元素",
    "faqJsonAPathCurrrent": "当前对象/元素",
    "faqJsonAPathChild": "子成员操作员",
    "faqJsonAPathDecendant": "递归后代运算符",
    "faqJsonAPathAll": "通配符匹配所有对象/元素，无论其名称如何",
    "faqJsonAPathSubscript": "下标运算符",
    "faqJsonAPathUnion": "作为集合的替代名称或数组索引的联合运算符",
    "faqJsonAPathFilter": "通过静态评估应用过滤器（脚本）表达式",
    "faqJsonAPathScript": "通过静态评估进行脚本表达",
    "faqJsonAPathNote": "注意：在JsonPath表达式中仅支持单引号。JSONPath位置中的脚本表达式不会被JsonPath递归评估。只有全局$和局部@符号通过简单的正则表达式进行扩展。本应用不验证您提供的JsonPath。如果JsonPath无效或不匹配任何数据，它将被忽略。调试时请使用文本和日志面板。",
    "faqJsonAPublishTitle": "发布JSON数据：",
    "faqJsonAPublish": "您可以将发布的数据封装成JSON格式。例如，您将{\"kitchen\": {\"fan\": \"<payload>\"}}配置为JSON模式。现在如果您将滑块值设置为10，那么<payload>将被替换为10，最终将发布{\"kitchen\": {\"fan\": \"10\"}}。您可以根据具体情况使用多个可替换变量，如<timestamp>、<client-id>等。要了解所有可用变量，请在配置面板时按下内联帮助按钮。",
    "faqJsonATest": "您可以使用此第三方网站测试JSON路径。",
    "faqBackgroundQ": "是否可以在后台运行并自动连接？",
    "faqBackgroundA": "是的，它可以在Android后台运行并在连接丢失时自动连接。在iOS上，如果它在前台运行并且“保持屏幕常亮”设置已打开，它可以连续运行。",
    "faqNotificationQ": "它有通知功能吗？",
    "faqNotificationA": "通知功能仅在Android专业版中可用。您可以启用或禁用任何面板的通知。",
    "faqDashboardPrefixQ": "什么是仪表板前缀？",
    "faqDashboardPrefixA": "当您配置仪表板前缀时，它将自动添加到同一仪表板下所有面板的主题之前。这对公共代理很有帮助。请参阅用户指南以获取详细说明。",
    "faqComboPanelQ": "我们可以合并多个面板吗？",
    "faqComboPanelA": "是的，您可以直观地合并相同或不同类型的面板。要组合面板，请使用面板选项中的合并功能。这将移除特定一侧的面板边框，并显示为组合面板。",
    "faqTimestampQ": "可以显示已发送和接收消息的时间戳吗？",
    "faqTimestampA": "是的，您可以为任何面板打开此功能。请记住，这仅显示代理视角的时间戳，即显示消息何时传递给代理或传递到手机。",
    "faqMaxStorageQ": "消息存储的最大限制是什么？",
    "faqMaxStorageA": "对于大多数面板，只有最后一条消息是相关的。然而，一些面板如日志和折线图可以存储以前的消息。每个面板每个主题可以存储1000条消息。",
    "faqSummary": "希望这些常见问题对您有用。详细信息请参阅《用户指南》。如果您有任何疑问，请随时通过以下方式联系我们",
    "faqClientCertificateAopenssl": "在客户端中打开SSL pkcs12 -遗留 -导出 -证书。CRT -inkey 客户端。Key -out 客户端.p12（原英文：openssl pkcs12 -legacy -export -clcerts -in client.crt -inkey client.key -out client.p12）",
    "useIconButton": "为按钮使用图标",
    "panelWidth75": "3/4屏宽"
}